LICENSE.txt
MANIFEST.in
README
requirements.txt
setup.cfg
setup.py
Pinch/APIException.py
Pinch/APIHelper.py
Pinch/Configuration.py
Pinch/CustomAuthUtility.py
Pinch/Decorators.py
Pinch/PinchClient.py
Pinch/__init__.py
Pinch.egg-info/PKG-INFO
Pinch.egg-info/SOURCES.txt
Pinch.egg-info/dependency_links.txt
Pinch.egg-info/top_level.txt
Pinch/Controllers/BaseController.py
Pinch/Controllers/TicketController.py
Pinch/Controllers/WebhookController.py
Pinch/Controllers/WebhookTypeController.py
Pinch/Controllers/__init__.py
Pinch/Http/HttpClient.py
Pinch/Http/HttpMethodEnum.py
Pinch/Http/HttpRequest.py
Pinch/Http/HttpResponse.py
Pinch/Http/RequestsClient.py
Pinch/Http/__init__.py
Pinch/Models/BaseModel.py
Pinch/Models/Building.py
Pinch/Models/Document.py
Pinch/Models/Person.py
Pinch/Models/Ticket.py
Pinch/Models/Unit.py
Pinch/Models/Webhook.py
Pinch/Models/WebhookType.py
Pinch/Models/__init__.py