Metadata-Version: 1.1
Name: Pinch
Version: 0.1.7
Summary: A simple gem to easily connect to the Inch Housing Intervention Interface
Home-page: https://github.com/Uelb/pinch-python
Author: Inch
Author-email: thomas@inchbase.com
License: UNKNOWN
Download-URL: https://github.com/Uelb/pinch-python/tarball/v0.1.7
Keywords: company,api,housing,intervention,geronimo,inch
Platform: UNKNOWN
